{"昌吉学院":[{"slug":"ccpc__ccpc2023__ccpc2023harbin","title":"第 9 届 CCPC 中国大学生程序设计竞赛 哈尔滨站","startAt":"2023-11-05T09:00:00+08:00","teamRank":244,"teamCount":253,"schoolRank":155,"schoolCount":159,"perf":1260.67,"delta":-46.17}],"长春建筑学院":[{"slug":"provincial__jl__jlcpc19th","title":"第 19 届吉林省大学生程序设计竞赛","startAt":"2026-05-23T09:00:00+08:00","teamRank":144,"teamCount":155,"schoolRank":24,"schoolCount":25,"perf":1348.38,"delta":-9.71},{"slug":"ccpc__ccpc2024__ccpc2024invitational-changchun","title":"2024年中国大学生程序设计竞赛全国邀请赛（长春）暨第十七届CCPC吉林省大学生程序设计竞赛","startAt":"2024-05-18T09:00:00+08:00","teamRank":100,"teamCount":181,"schoolRank":31,"schoolCount":38,"perf":1403.92,"delta":-11.03}],"Beijing Jiaotong University, Weihai":[{"slug":"provincial__jx__jxcpc2025","title":"2025年icpc全国邀请赛（南昌）暨2025年（icpc）江西省大学生程序设计竞赛 - 正式赛","startAt":"2025-05-18T10:00:00+08:00","teamRank":111,"teamCount":457,"schoolRank":89,"schoolCount":301,"perf":1576.02,"delta":7.09},{"slug":"icpc__icpc2024__icpc2024hongkong","title":"第 49 届 ICPC 国际大学生程序设计竞赛区域赛香港站","startAt":"2024-12-22T09:10:00+08:00","teamRank":66,"teamCount":174,"schoolRank":42,"schoolCount":115,"perf":1552.61,"delta":7.38}],"Xihua University":[{"slug":"icpc__icpc2025__icpc2025hongkong","title":"The 50th ICPC Asia Hong Kong Regional Contest","startAt":"2025-11-30T09:00:00+08:00","teamRank":94,"teamCount":136,"schoolRank":84,"schoolCount":119,"perf":1441.03,"delta":-11.48},{"slug":"provincial__jx__jxcpc2025","title":"2025年icpc全国邀请赛（南昌）暨2025年（icpc）江西省大学生程序设计竞赛 - 正式赛","startAt":"2025-05-18T10:00:00+08:00","teamRank":164,"teamCount":457,"schoolRank":125,"schoolCount":301,"perf":1533.32,"delta":1.78},{"slug":"icpc__icpc2024__icpc2024hongkong","title":"第 49 届 ICPC 国际大学生程序设计竞赛区域赛香港站","startAt":"2024-12-22T09:10:00+08:00","teamRank":72,"teamCount":174,"schoolRank":46,"schoolCount":115,"perf":1538.49,"delta":4.55}],"Hangzhou Normal University":[{"slug":"provincial__jx__jxcpc2025","title":"2025年icpc全国邀请赛（南昌）暨2025年（icpc）江西省大学生程序设计竞赛 - 正式赛","startAt":"2025-05-18T10:00:00+08:00","teamRank":83,"teamCount":457,"schoolRank":69,"schoolCount":301,"perf":1610.77,"delta":14.92},{"slug":"icpc__icpc2024__icpc2024hongkong","title":"第 49 届 ICPC 国际大学生程序设计竞赛区域赛香港站","startAt":"2024-12-22T09:10:00+08:00","teamRank":122,"teamCount":174,"schoolRank":82,"schoolCount":115,"perf":1432.92,"delta":-16.56}],"Chengdu University of Information Technology":[{"slug":"icpc__icpc2025__icpc2025hongkong","title":"The 50th ICPC Asia Hong Kong Regional Contest","startAt":"2025-11-30T09:00:00+08:00","teamRank":42,"teamCount":136,"schoolRank":37,"schoolCount":119,"perf":1597.16,"delta":8.07},{"slug":"provincial__jx__jxcpc2025","title":"2025年icpc全国邀请赛（南昌）暨2025年（icpc）江西省大学生程序设计竞赛 - 正式赛","startAt":"2025-05-18T10:00:00+08:00","teamRank":17,"teamCount":457,"schoolRank":13,"schoolCount":301,"perf":1736.85,"delta":35.84}],"Wuhan College":[{"slug":"provincial__jx__jxcpc2025","title":"2025年icpc全国邀请赛（南昌）暨2025年（icpc）江西省大学生程序设计竞赛 - 正式赛","startAt":"2025-05-18T10:00:00+08:00","teamRank":313,"teamCount":457,"schoolRank":229,"schoolCount":301,"perf":1402.58,"delta":-17.65}],"大连理工大学盘锦校区(非独立法人)":[{"slug":"icpc__icpc2025__icpc2025ec-online2","title":"2025 ICPC Asia EC网络预选赛 - 第二场","startAt":"2025-09-14T13:00:00+08:00","teamRank":473,"teamCount":2575,"schoolRank":135,"schoolCount":488,"perf":1615.17,"delta":25.5}],"芜湖学院":[{"slug":"icpc__icpc2025__icpc2025ec-online2","title":"2025 ICPC Asia EC网络预选赛 - 第二场","startAt":"2025-09-14T13:00:00+08:00","teamRank":1757,"teamCount":2575,"schoolRank":409,"schoolCount":488,"perf":1288.93,"delta":-39.75}],"China University of Geosciences, Beijing":[{"slug":"icpc__icpc2025__icpc2025hongkong","title":"The 50th ICPC Asia Hong Kong Regional Contest","startAt":"2025-11-30T09:00:00+08:00","teamRank":75,"teamCount":136,"schoolRank":67,"schoolCount":119,"perf":1474.28,"delta":-7.3}],"武汉外国语学校":[{"slug":"icpc__icpc2026__icpc2026invitational-wuhan","title":"2026 年 ICPC 国际大学生程序设计竞赛全国邀请赛（武汉）暨湖北省赛","startAt":"2026-05-17T09:30:00+08:00","teamRank":5,"teamCount":236,"schoolRank":5,"schoolCount":191,"perf":1931.78,"delta":68.04}],"睿钯科技":[{"slug":"icpc__icpc2026__icpc2026invitational-wuhan","title":"2026 年 ICPC 国际大学生程序设计竞赛全国邀请赛（武汉）暨湖北省赛","startAt":"2026-05-17T09:30:00+08:00","teamRank":139,"teamCount":236,"schoolRank":113,"schoolCount":191,"perf":1467.38,"delta":-6.27}]}