{"哈尔滨师范大学":[{"slug":"provincial__northeast__northeastcpc20th","title":"第二十届东北地区大学生程序设计竞赛","startAt":"2026-05-24T09:00:00+08:00","teamRank":111,"teamCount":182,"schoolRank":36,"schoolCount":51,"perf":1395.06,"delta":-1.98},{"slug":"provincial__hl__hlcpc21st","title":"第二十一届黑龙江省大学生程序设计竞赛","startAt":"2026-05-10T09:00:00+08:00","teamRank":92,"teamCount":206,"schoolRank":11,"schoolCount":20,"perf":1463.71,"delta":2.66},{"slug":"provincial__hl__hlcpc20th","title":"第二十届黑龙江省大学生程序设计竞赛","startAt":"2025-05-11T09:00:00+08:00","teamRank":84,"teamCount":187,"schoolRank":12,"schoolCount":19,"perf":1440.14,"delta":1.39},{"slug":"ccpc__ccpc2022__ccpc2022ladies","title":"2022 中国大学生程序设计竞赛（女生专场）","startAt":"2022-11-27T09:00:00+08:00","teamRank":213,"teamCount":277,"schoolRank":140,"schoolCount":156,"perf":1323.79,"delta":-9.27},{"slug":"ccpc__ccpc2021__ccpc2021harbin","title":"第 7 届中国大学生程序设计竞赛（CCPC）哈尔滨站","startAt":"2021-11-28T09:00:00+08:00","teamRank":302,"teamCount":317,"schoolRank":146,"schoolCount":149,"perf":1319.68,"delta":-26.18},{"slug":"ccpc__ccpc2021__ccpc2021ladies","title":"2021年中国大学生程序设计竞赛 女生专场赛","startAt":"2021-10-31T09:00:00+08:00","teamRank":189,"teamCount":258,"schoolRank":128,"schoolCount":161,"perf":1393.37,"delta":-9.79}],"山东协和学院":[{"slug":"provincial__sd__sdcpc16th","title":"2026年山东省大学生程序设计竞赛正式赛（山东大学）","startAt":"2026-05-24T09:30:00+08:00","teamRank":121,"teamCount":294,"schoolRank":26,"schoolCount":39,"perf":1398.45,"delta":1.14},{"slug":"ccpc__ccpc2025__ccpc2025invitational-fujian","title":"第十二届福建省大学生程序设计竞赛暨2025年CCPC福建邀请赛","startAt":"2025-06-21T12:00:00+08:00","teamRank":174,"teamCount":285,"schoolRank":130,"schoolCount":176,"perf":1368.1,"delta":-1.35},{"slug":"provincial__sd__sdcpc15th","title":"2025年山东省大学生程序设计竞赛（山东大学）","startAt":"2025-05-25T09:30:00+08:00","teamRank":187,"teamCount":271,"schoolRank":29,"schoolCount":33,"perf":1316.95,"delta":-3.67},{"slug":"icpc__icpc2025__icpc2025invitational-wuhan","title":"第 50 届 ICPC 国际大学生程序设计竞赛邀请赛武汉站","startAt":"2025-04-27T10:00:00+08:00","teamRank":213,"teamCount":308,"schoolRank":129,"schoolCount":178,"perf":1393.55,"delta":-0.68},{"slug":"icpc__icpc2024__icpc2024preliminary-1","title":"The 49th ICPC Asia Regionals Online Contest (I)","startAt":"2024-09-15T13:00:00+08:00","teamRank":930,"teamCount":2323,"schoolRank":275,"schoolCount":449,"perf":1419.89,"delta":2.47},{"slug":"ccpc__ccpc2024__ccpc2024invitational-jinan","title":"“齐鲁软件园杯”2024年中国大学生程序设计竞赛全国邀请赛（山东）暨CCPC山东省大学生程序设计竞赛","startAt":"2024-05-26T09:30:00+08:00","teamRank":274,"teamCount":504,"schoolRank":114,"schoolCount":145,"perf":1364.42,"delta":-4.78},{"slug":"icpc__icpc2023__icpc2023jinan","title":"第 48 届国际大学生程序设计竞赛亚洲区域赛济南站","startAt":"2023-12-03T09:30:00+08:00","teamRank":332,"teamCount":347,"schoolRank":211,"schoolCount":217,"perf":1297.53,"delta":-20.61},{"slug":"icpc__icpc2023__icpc2023preliminary-2","title":"The 2023 ICPC Asia Regionals Online Contest (II)","startAt":"2023-09-23T12:00:00+08:00","teamRank":1656,"teamCount":2726,"schoolRank":353,"schoolCount":428,"perf":1348.69,"delta":-15.61},{"slug":"icpc__icpc2022__icpc2022preliminary-2","title":"The 2022 ICPC Asia Regionals Online Contest (II)","startAt":"2022-09-25T12:00:00+08:00","teamRank":1942,"teamCount":2755,"schoolRank":386,"schoolCount":428,"perf":1300.84,"delta":-36.01}],"空军工程大学":[{"slug":"icpc__icpc2026__icpc2026invitational-xi_an","title":"第 51 届 ICPC 国际大学生程序设计竞赛邀请赛西安站 - 正式赛","startAt":"2026-05-02T10:00:00+08:00","teamRank":381,"teamCount":400,"schoolRank":219,"schoolCount":225,"perf":1288.26,"delta":-25.37},{"slug":"icpc__icpc2022__icpc2022xi_an","title":"第 47 届国际大学生程序设计竞赛亚洲区域西安站","startAt":"2022-11-13T12:00:00+08:00","teamRank":383,"teamCount":522,"schoolRank":185,"schoolCount":247,"perf":1416.9,"delta":-15.02}],"City University of Macau":[{"slug":"icpc__icpc2024__icpc2024hongkong","title":"第 49 届 ICPC 国际大学生程序设计竞赛区域赛香港站","startAt":"2024-12-22T09:10:00+08:00","teamRank":174,"teamCount":174,"schoolRank":115,"schoolCount":115,"perf":1347.96,"delta":-33.55}],"China University of Petroleum,Beijing":[{"slug":"provincial__jx__jxcpc2025","title":"2025年icpc全国邀请赛（南昌）暨2025年（icpc）江西省大学生程序设计竞赛 - 正式赛","startAt":"2025-05-18T10:00:00+08:00","teamRank":23,"teamCount":457,"schoolRank":18,"schoolCount":301,"perf":1736.85,"delta":35.84}],"Shandong Normal University":[{"slug":"provincial__jx__jxcpc2025","title":"2025年icpc全国邀请赛（南昌）暨2025年（icpc）江西省大学生程序设计竞赛 - 正式赛","startAt":"2025-05-18T10:00:00+08:00","teamRank":97,"teamCount":457,"schoolRank":78,"schoolCount":301,"perf":1595.92,"delta":13.29}],"Xuhai College, China University of Mining and Technology":[{"slug":"provincial__jx__jxcpc2025","title":"2025年icpc全国邀请赛（南昌）暨2025年（icpc）江西省大学生程序设计竞赛 - 正式赛","startAt":"2025-05-18T10:00:00+08:00","teamRank":320,"teamCount":457,"schoolRank":234,"schoolCount":301,"perf":1402.58,"delta":-17.65}],"澳门城市大学":[{"slug":"icpc__icpc2025__icpc2025hongkong","title":"The 50th ICPC Asia Hong Kong Regional Contest","startAt":"2025-11-30T09:00:00+08:00","teamRank":117,"teamCount":136,"schoolRank":105,"schoolCount":118,"perf":1349.55,"delta":-29.51}],"清远职业技术学院":[{"slug":"provincial__gd__gdcpc23rd","title":"广东省第二十三届大学生程序设计竞赛","startAt":"2026-05-17T10:40:00+08:00","teamRank":275,"teamCount":298,"schoolRank":44,"schoolCount":44,"perf":1277.08,"delta":-21.3}]}