{"中国人民公安大学":[{"slug":"ccpc__ccpc2025__ccpc2025-online","title":"2025年CCPC网络预选赛","startAt":"2025-09-20T13:00:00+08:00","teamRank":1980,"teamCount":2085,"schoolRank":439,"schoolCount":443,"perf":1209.42,"delta":-40.97},{"slug":"icpc__icpc2022__icpc2022-online-qual2","title":"The 2022 ICPC Asia Regionals Online Contest (II)","startAt":"2022-09-25T12:00:00+08:00","teamRank":1835,"teamCount":2755,"schoolRank":375,"schoolCount":428,"perf":1337.13,"delta":-28.74}],"河北经贸大学经济管理学院":[{"slug":"ccpc__ccpc2026__ccpc2026invitational-qinhuangdao","title":"2026年中国大学生程序设计竞赛全国邀请赛（秦皇岛）暨第十届河北省大学生程序设计竞赛-正式赛","startAt":"2026-05-24T08:30:00+08:00","teamRank":335,"teamCount":375,"schoolRank":126,"schoolCount":131,"perf":1304.81,"delta":-15.15},{"slug":"provincial__he__hecpc9th","title":"第九届河北省大学生程序设计竞赛 - 正式赛","startAt":"2025-05-18T09:00:00+08:00","teamRank":152,"teamCount":221,"schoolRank":47,"schoolCount":56,"perf":1364.17,"delta":-7.45},{"slug":"provincial__he__hecpc8th","title":"2024 CCPC 河北省大学生程序设计竞赛 - 正式赛","startAt":"2024-05-26T09:00:00+08:00","teamRank":154,"teamCount":209,"schoolRank":44,"schoolCount":50,"perf":1371.23,"delta":-8.7},{"slug":"provincial__he__hecpc7th","title":"2023 年 CCPC 河北省大学生程序设计竞赛（东北大学秦皇岛分校）","startAt":"2023-05-21T09:00:00+08:00","teamRank":167,"teamCount":262,"schoolRank":46,"schoolCount":54,"perf":1388.71,"delta":-9.63}],"Beijing Institute of Graphic Communication":[{"slug":"icpc__icpc2024__icpc2024hongkong","title":"第 49 届 ICPC 国际大学生程序设计竞赛区域赛香港站","startAt":"2024-12-22T09:10:00+08:00","teamRank":140,"teamCount":174,"schoolRank":90,"schoolCount":115,"perf":1412.06,"delta":-20.73}],"Qingdao University of Technology":[{"slug":"provincial__jx__jxcpc2025","title":"2025年icpc全国邀请赛（南昌）暨2025年（icpc）江西省大学生程序设计竞赛 - 正式赛","startAt":"2025-05-18T10:00:00+08:00","teamRank":248,"teamCount":457,"schoolRank":184,"schoolCount":301,"perf":1452.23,"delta":-9.7}]}